xespresso/__init__.py
xespresso/cohp.py
xespresso/dos.py
xespresso/hpxespresso.py
xespresso/input_parameters.py
xespresso/neb.py
xespresso/scheduler.py
xespresso/tools.py
xespresso/uscsd.py
xespresso/xespresso.py
xespresso/xio.py
xespresso/xlog.py
xespresso/data/__init__.py
xespresso/data/pseudo.py
xespresso/post/__init__.py
xespresso/post/bands.py
xespresso/post/base.py
xespresso/post/dos.py
xespresso/post/dynmat.py
xespresso/post/hp.py
xespresso/post/matdyn.py
xespresso/post/nscf.py
xespresso/post/ph.py
xespresso/post/pp.py
xespresso/post/projwfc.py
xespresso/post/q2r.py
xespresso/utils/__init__.py
xespresso/utils/qe_dos_parser.py
xespresso/utils/xml_parser.py
xespresso/workflow/__init__.py
xespresso/workflow/base.py
xespresso/workflow/oer.py
xespresso/workflow/phonon.py
xespresso-1.5.5.dist-info/LICENSE
xespresso-1.5.5.dist-info/METADATA
xespresso-1.5.5.dist-info/WHEEL
xespresso-1.5.5.dist-info/top_level.txt
xespresso-1.5.5.dist-info/RECORD
