Metadata-Version: 2.1
Name: xespresso
Version: 1.5.5
Summary: Quantum ESPRESSO Calculator for Atomic Simulation Environment (ASE).
Home-page: https://github.com/superstar54/xespresso
Author: Xing Wang
Author-email: xingwang1991@gmail.com
License: GPL
Classifier: License :: OSI Approved :: GNU General Public License v3 (GPLv3)
Classifier: Programming Language :: Python :: 3.5
Requires-Python: >=3.5
License-File: LICENSE
Requires-Dist: ase
Requires-Dist: numpy
Requires-Dist: scipy
Requires-Dist: matplotlib
